alhazen.py
alhazen-1.4.1.dist-info/LICENSE
alhazen-1.4.1.dist-info/METADATA
alhazen-1.4.1.dist-info/WHEEL
alhazen-1.4.1.dist-info/top_level.txt
alhazen-1.4.1.dist-info/RECORD
