Metadata-Version: 2.1
Name: alhazen
Version: 1.4.1
Summary: A simple framework to facilitate running experiments, written in Python, using cognitive models, or similar applications, in multiple, parallel processes
Home-page: https://cmu-psych-fms.github.io/fms/alhazen/index.html
Author: Don Morrison
Author-email: dfm2@cmu.edu
License: UNKNOWN
Platform: any
Classifier: Intended Audience :: Science/Research
Classifier: License :: OSI Approved :: MIT License
Classifier: Programming Language :: Python
Classifier: Programming Language :: Python :: 3 :: Only
Classifier: Programming Language :: Python :: 3.7
Classifier: Programming Language :: Python :: 3.8
Classifier: Programming Language :: Python :: 3.9
Classifier: Programming Language :: Python :: 3.10
Classifier: Programming Language :: Python :: 3.11
Classifier: Programming Language :: Python :: 3.12
Classifier: Programming Language :: Python :: 3.13
Classifier: Operating System :: OS Independent
Requires-Python: >=3.7
License-File: LICENSE
Requires-Dist: tqdm
